py4pm/__init__.py
py4pm/chemutilities.py
py4pm/dateutilities.py
py4pm/deltaTool.py
py4pm/pmfutilities.py
py4pm-0.6.5.dist-info/METADATA
py4pm-0.6.5.dist-info/WHEEL
py4pm-0.6.5.dist-info/top_level.txt
py4pm-0.6.5.dist-info/RECORD
