Metadata-Version: 2.1
Name: py4pm
Version: 0.6.5
Summary: UNKNOWN
Home-page: https://gricad-gitlab.univ-grenoble-alpes.fr/webersa/py4pm
Author: Samuël Weber
Author-email: samuel.weber@univ-grenoble-alpes.fr
License: UNKNOWN
Project-URL: Documentation, https://py4pm.readthedocs.io/en/latest/
Project-URL: Source, https://gricad-gitlab.univ-grenoble-alpes.fr/webersa/py4pm
Platform: UNKNOWN
Classifier: Development Status :: 3 - Alpha
Classifier: Intended Audience :: Science/Research
Classifier: Topic :: Scientific/Engineering :: Atmospheric Science
Classifier: Programming Language :: Python :: 3
Requires-Python: >=3
Requires-Dist: matplotlib
Requires-Dist: pandas
Requires-Dist: seaborn
Requires-Dist: xlrd
